pyard/__init__.py
pyard/pyard_legacy.py
pyard-1.0.5.dist-info/LICENSE
pyard-1.0.5.dist-info/METADATA
pyard-1.0.5.dist-info/WHEEL
pyard-1.0.5.dist-info/top_level.txt
pyard-1.0.5.dist-info/RECORD
