Metadata-Version: 2.1
Name: pyard
Version: 1.0.5
Summary: This is not the pyard you're looking for.
Home-page: https://github.com/nmdp-bioinformatics/pyard-legacy
Author: Pradeep Bashyal
Author-email: pbashyal@nmdp.org
License: LGPL 3.0
Classifier: Development Status :: 2 - Pre-Alpha
Classifier: Intended Audience :: Developers
Classifier: License :: OSI Approved :: GNU Lesser General Public License v3 (LGPLv3)
Classifier: Natural Language :: English
Classifier: Programming Language :: Python :: 3.8
Classifier: Programming Language :: Python :: 3.9
Classifier: Programming Language :: Python :: 3.10
Requires-Python: >=3.8
License-File: LICENSE
